rdflib_sqlite3/__init__.py
rdflib_sqlite3/store.py
rdflib_sqlite3-0.1.0.dist-info/METADATA
rdflib_sqlite3-0.1.0.dist-info/WHEEL
rdflib_sqlite3-0.1.0.dist-info/licenses/COPYING
rdflib_sqlite3-0.1.0.dist-info/RECORD
