Metadata-Version: 2.3
Name: rdflib-sqlite3
Version: 0.1.0
Summary: SQLite-backed RDFLib store
Project-URL: Homepage, https://codeberg.org/ctrlall/rdflib-sqlie3
Project-URL: Bug Tracker, https://codeberg.org/ctrlall/rdflib-sqlite3/issues
Author-email: pukkamustard <pukkamustard@posteo.net>, Moritz Feichtinger <moritz.feichtinger@unibas.ch>
License: GNU AFFERO GENERAL PUBLIC LICENSE
License-File: COPYING
Classifier: License :: OSI Approved :: GNU Affero General Public License v3 or later (AGPLv3+)
Classifier: Operating System :: OS Independent
Classifier: Programming Language :: Python :: 3
Requires-Python: >=3.10
Requires-Dist: rdflib
Requires-Dist: rdflib-rdfcbor
